test.py
romiserial/__init__.py
romiserial/device.py
romiserial/test.py
romiserial-0.1.2.dist-info/licenses/LICENSE
romiserial-0.1.2.dist-info/METADATA
romiserial-0.1.2.dist-info/WHEEL
romiserial-0.1.2.dist-info/top_level.txt
romiserial-0.1.2.dist-info/RECORD
