Metadata-Version: 2.4
Name: romiserial
Version: 0.1.2
Summary: A library for serial communication (UART) with improved error detection and recovery
Author-email: "Peter Hanappe, Doug Boari" <peter.hanappe@sony.com>
License-Expression: LGPL-2.1
Project-URL: Homepage, https://github.com/romi/RomiSerial
Classifier: Programming Language :: Python :: 3
Classifier: Operating System :: OS Independent
Classifier: Intended Audience :: Developers
Classifier: Topic :: Software Development :: Embedded Systems
Requires-Python: >=3.8
License-File: LICENSE
Requires-Dist: pyserial
Requires-Dist: crc8
Dynamic: license-file
